MANIFEST.in
setup.cfg
setup.py
versioneer.py
scicfg/__init__.py
scicfg/_version.py
scicfg/configs.py
scicfg.egg-info/PKG-INFO
scicfg.egg-info/SOURCES.txt
scicfg.egg-info/dependency_links.txt
scicfg.egg-info/pbr.json
scicfg.egg-info/top_level.txt