Metadata-Version: 1.1
Name: scicfg
Version: 1.0.1
Summary: A python hierarchical configuration structure for scientific parameter files
Home-page: https://github.com/humm/scicfg
Author: Fabien Benureau
Author-email: fabien.benureau+scicfg@gmail.com
License: LGPLv3
Download-URL: https://github.com/humm/scicfg/tarball/1.0.1
Platform: UNKNOWN
Classifier: Development Status :: 4 - Beta
Classifier: License :: OSI Approved :: GNU Lesser General Public License v3 (LGPLv3)
Classifier: Programming Language :: Python :: 2.7
Classifier: Intended Audience :: Developers
Classifier: Intended Audience :: Science/Research
